Metadata-Version: 1.1
Name: supersltools
Version: 0.0.1
Summary: tools for work
Home-page: UNKNOWN
Author: Snehashish Laskar
Author-email: <snehashish.laskar@gmail.com>
License: UNKNOWN
Keywords: python,video,stream,video stream,camera stream,sockets
Platform: UNKNOWN
Classifier: Development Status :: 1 - Planning
Classifier: Intended Audience :: Developers
Classifier: Programming Language :: Python :: 3
Classifier: Operating System :: Unix
Classifier: Operating System :: MacOS :: MacOS X
Classifier: Operating System :: Microsoft :: Windows
